lazycrud/__init__.py
lazycrud/context_processors.py
lazycrud/forms.py
lazycrud/models.py
lazycrud/utils.py
lazycrud/locale/de/LC_MESSAGES/django.mo
lazycrud/locale/de/LC_MESSAGES/django.po
lazycrud/locale/es/LC_MESSAGES/django.mo
lazycrud/locale/es/LC_MESSAGES/django.po
lazycrud/locale/fr/LC_MESSAGES/django.mo
lazycrud/locale/fr/LC_MESSAGES/django.po
lazycrud/locale/it/LC_MESSAGES/django.mo
lazycrud/locale/it/LC_MESSAGES/django.po
lazycrud/static/lazycrud/css/dataTables.bootstrap.css
lazycrud/static/lazycrud/css/dataTables.fontAwesome.css
lazycrud/static/lazycrud/css/datatables.min.css
lazycrud/static/lazycrud/css/datepicker3.css
lazycrud/static/lazycrud/css/datetimepicker.min.css
lazycrud/static/lazycrud/css/fixedHeader.dataTables.min.css
lazycrud/static/lazycrud/js/object_form.js
lazycrud/static/lazycrud/js/object_list.js
lazycrud/static/lazycrud/js/bootstrap-datepicker/bootstrap-datepicker.it.js
lazycrud/static/lazycrud/js/bootstrap-datepicker/bootstrap-datepicker.js
lazycrud/static/lazycrud/js/bootstrap-datetimepicker/datetimepicker.min.js
lazycrud/static/lazycrud/js/dataTables/dataTables.bootstrap.js
lazycrud/static/lazycrud/js/dataTables/dataTables.fixedHeader.min.js
lazycrud/static/lazycrud/js/dataTables/datatables.min.js
lazycrud/static/lazycrud/js/dataTables/datetime-moment.js
lazycrud/static/lazycrud/js/dataTables/jquery.dataTables.js
lazycrud/static/lazycrud/js/dataTables/moment.min.js
lazycrud/static/lazycrud/js/dataTables/i18n/de.js
lazycrud/static/lazycrud/js/dataTables/i18n/es.js
lazycrud/static/lazycrud/js/dataTables/i18n/fr.js
lazycrud/static/lazycrud/js/dataTables/i18n/it.js
lazycrud/static/lazycrud/js/moment/it.js
lazycrud/static/lazycrud/js/moment/moment-with-locales.min.js
lazycrud/static/lazycrud/js/moment/moment.js
lazycrud/templates/lazycrud/_datatables_css.html
lazycrud/templates/lazycrud/_datatables_js.html
lazycrud/templates/lazycrud/_headers_row.html
lazycrud/templates/lazycrud/_table.html
django_lazycrud-1.8.6.dist-info/LICENSE.txt
django_lazycrud-1.8.6.dist-info/METADATA
django_lazycrud-1.8.6.dist-info/WHEEL
django_lazycrud-1.8.6.dist-info/top_level.txt
django_lazycrud-1.8.6.dist-info/RECORD
