Metadata-Version: 2.1
Name: django-lazycrud
Version: 1.8.6
Summary: A little Django app to reduce boilerplate code at a minimum when you write class based views in a typical CRUD scenario.
Home-page: https://github.com/baxeico/django-lazycrud
Author: Augusto Destrero
Author-email: a.destrero@gmail.com
License: MIT
Keywords: django,crud
License-File: LICENSE.txt
Requires-Dist: django-crispy-forms>=1.6.1
